pybindgen/__init__.py
pybindgen/castxmlparser.py
pybindgen/container.py
pybindgen/converter_functions.py
pybindgen/cppattribute.py
pybindgen/cppclass.py
pybindgen/cppclass_container.py
pybindgen/cppcustomattribute.py
pybindgen/cppexception.py
pybindgen/cppmethod.py
pybindgen/enum.py
pybindgen/function.py
pybindgen/module.py
pybindgen/overloading.py
pybindgen/pytypeobject.py
pybindgen/settings.py
pybindgen/utils.py
pybindgen/version.py
pybindgen/wrapper_registry.py
pybindgen/typehandlers/__init__.py
pybindgen/typehandlers/base.py
pybindgen/typehandlers/booltype.py
pybindgen/typehandlers/codesink.py
pybindgen/typehandlers/doubletype.py
pybindgen/typehandlers/floattype.py
pybindgen/typehandlers/inttype.py
pybindgen/typehandlers/pyobjecttype.py
pybindgen/typehandlers/smart_ptr.py
pybindgen/typehandlers/stringtype.py
pybindgen/typehandlers/voidtype.py
pybindgen/typehandlers/ctypeparser/__init__.py
pybindgen/typehandlers/ctypeparser/tokenizer.py
PyBindGen-0.22.0.dist-info/AUTHORS
PyBindGen-0.22.0.dist-info/COPYING
PyBindGen-0.22.0.dist-info/METADATA
PyBindGen-0.22.0.dist-info/WHEEL
PyBindGen-0.22.0.dist-info/top_level.txt
PyBindGen-0.22.0.dist-info/RECORD
