Metadata-Version: 1.1
Name: PyBindGen
Version: 0.22.0
Summary: Python Bindings Generator
Home-page: https://github.com/gjcarneiro/pybindgen
Author: Gustavo Carneiro
Author-email: gjcarneiro@gmail.com
License: UNKNOWN
Platform: UNKNOWN
Classifier: Development Status :: 4 - Beta
Classifier: Intended Audience :: Developers
Classifier: Topic :: Software Development :: Build Tools
Classifier: License :: OSI Approved :: GNU Lesser General Public License v2 or later (LGPLv2+)
Classifier: Programming Language :: Python :: 2
Classifier: Programming Language :: Python :: 3
